odoo8_addon_document_reindex-8.0.1.0.0.99.dev6-py2.7-nspkg.pth
odoo8_addon_document_reindex-8.0.1.0.0.99.dev6.dist-info/top_level.txt
odoo8_addon_document_reindex-8.0.1.0.0.99.dev6.dist-info/WHEEL
odoo8_addon_document_reindex-8.0.1.0.0.99.dev6.dist-info/RECORD
odoo8_addon_document_reindex-8.0.1.0.0.99.dev6.dist-info/metadata.json
odoo8_addon_document_reindex-8.0.1.0.0.99.dev6.dist-info/DESCRIPTION.rst
odoo8_addon_document_reindex-8.0.1.0.0.99.dev6.dist-info/METADATA
odoo8_addon_document_reindex-8.0.1.0.0.99.dev6.dist-info/namespace_packages.txt
odoo_addons/document_reindex/__openerp__.py
odoo_addons/document_reindex/hooks.py
odoo_addons/document_reindex/__init__.py
odoo_addons/document_reindex/README.rst
odoo_addons/document_reindex/models/__init__.py
odoo_addons/document_reindex/models/ir_attachment.py
odoo_addons/document_reindex/models/knowledge_config_settings.py
odoo_addons/document_reindex/i18n/it.po
odoo_addons/document_reindex/i18n/es.po
odoo_addons/document_reindex/i18n/sl.po
odoo_addons/document_reindex/i18n/de.po
odoo_addons/document_reindex/views/knowledge_config_settings.xml
odoo_addons/document_reindex/views/ir_attachment.xml
odoo_addons/document_reindex/tests/__init__.py
odoo_addons/document_reindex/tests/test_reindex.py
odoo_addons/document_reindex/static/description/icon.png
